spidermatch/__init__.py
spidermatch/assets/icon_teal.png
spidermatch/assets/icon_transparent.png
spidermatch/assets/logo.png
spidermatch/assets/logo_dark.png
spidermatch/assets/logo_light.png
spidermatch/assets/spidermatch.icns
spidermatch/lib/__init__.py
spidermatch/lib/entities.py
spidermatch/lib/helpers.py
spidermatch/lib/search.py
spidermatch/main.py
spidermatch/windows/panel.ui
spidermatch/windows/rule.ui
spidermatch/windows/welcome.ui
spidermatch/worker.py
spidermatch-0.2.0.dist-info/LICENSE
spidermatch-0.2.0.dist-info/WHEEL
spidermatch-0.2.0.dist-info/entry_points.txt
spidermatch-0.2.0.dist-info/METADATA
spidermatch-0.2.0.dist-info/RECORD
