Metadata-Version: 2.1
Name: spidermatch
Version: 0.2.0
Summary: App for setting up automated spiders for incidents covered by local news in a certain country.
Home-page: https://github.com/agucova/spidermatch
Author: Agustín Covarrubias
Author-email: agucova@uc.cl
Requires-Python: >=3.8,<3.12
Classifier: Development Status :: 4 - Beta
Classifier: Environment :: MacOS X
Classifier: Environment :: Win32 (MS Windows)
Classifier: Environment :: X11 Applications
Classifier: Intended Audience :: Developers
Classifier: Intended Audience :: End Users/Desktop
Classifier: Natural Language :: Spanish
Classifier: Programming Language :: Python :: 3
Classifier: Programming Language :: Python :: 3.8
Classifier: Programming Language :: Python :: 3.9
Classifier: Programming Language :: Python :: 3.10
Classifier: Programming Language :: Python :: 3.11
Classifier: Programming Language :: Python :: 3
Classifier: Programming Language :: Python :: 3.8
Classifier: Programming Language :: Python :: 3.9
Classifier: Topic :: Communications :: Email
Classifier: Topic :: Office/Business
Classifier: Topic :: Software Development
Requires-Dist: PyQt6 (>=6.2.3,<7.0.0)
Requires-Dist: beartype (>=0.10.4,<0.11.0)
Requires-Dist: luqum (>=0.11.0,<0.12.0)
Requires-Dist: qt-material (>=2.10,<3.0)
Requires-Dist: rich (>=12.2.0,<13.0.0)
Requires-Dist: zenserp (>=0.2,<0.3)
